{"nodes": [{"id": "users_rokaskucinskas_development_ozy_sidecar_sidecar_store_py", "label": "store.py", "file_type": "code", "source_file": "sidecar/sidecar/store.py", "source_location": "L1"}, {"id": "sidecar_store_toolrow", "label": "ToolRow", "file_type": "code", "source_file": "sidecar/sidecar/store.py", "source_location": "L66"}, {"id": "sidecar_store_row_to_tool_row", "label": "_row_to_tool_row()", "file_type": "code", "source_file": "sidecar/sidecar/store.py", "source_location": "L83"}, {"id": "row", "label": "Row", "file_type": "code", "source_file": "sidecar/sidecar/store.py", "source_location": "L83"}, {"id": "sidecar_store_store", "label": "Store", "file_type": "code", "source_file": "sidecar/sidecar/store.py", "source_location": "L106"}, {"id": "sidecar_store_store_init", "label": ".__init__()", "file_type": "code", "source_file": "sidecar/sidecar/store.py", "source_location": "L116"}, {"id": "sidecar_store_store_close", "label": ".close()", "file_type": "code", "source_file": "sidecar/sidecar/store.py", "source_location": "L129"}, {"id": "sidecar_store_store_enter", "label": ".__enter__()", "file_type": "code", "source_file": "sidecar/sidecar/store.py", "source_location": "L136"}, {"id": "sidecar_store_store_exit", "label": ".__exit__()", "file_type": "code", "source_file": "sidecar/sidecar/store.py", "source_location": "L139"}, {"id": "sidecar_store_store_init_schema", "label": "._init_schema()", "file_type": "code", "source_file": "sidecar/sidecar/store.py", "source_location": "L144"}, {"id": "sidecar_store_store_get_meta", "label": ".get_meta()", "file_type": "code", "source_file": "sidecar/sidecar/store.py", "source_location": "L181"}, {"id": "sidecar_store_store_set_meta", "label": ".set_meta()", "file_type": "code", "source_file": "sidecar/sidecar/store.py", "source_location": "L189"}, {"id": "sidecar_store_store_get_by_toolref", "label": ".get_by_toolref()", "file_type": "code", "source_file": "sidecar/sidecar/store.py", "source_location": "L202"}, {"id": "sidecar_store_store_get_by_vector_id", "label": ".get_by_vector_id()", "file_type": "code", "source_file": "sidecar/sidecar/store.py", "source_location": "L212"}, {"id": "sidecar_store_store_iter_all", "label": ".iter_all()", "file_type": "code", "source_file": "sidecar/sidecar/store.py", "source_location": "L222"}, {"id": "sidecar_store_store_resolve_facet_allowlist", "label": ".resolve_facet_allowlist()", "file_type": "code", "source_file": "sidecar/sidecar/store.py", "source_location": "L238"}, {"id": "sidecar_store_store_compute_skip", "label": ".compute_skip()", "file_type": "code", "source_file": "sidecar/sidecar/store.py", "source_location": "L281"}, {"id": "sidecar_store_store_next_vector_id", "label": "._next_vector_id()", "file_type": "code", "source_file": "sidecar/sidecar/store.py", "source_location": "L304"}, {"id": "sidecar_store_store_upsert_one", "label": ".upsert_one()", "file_type": "code", "source_file": "sidecar/sidecar/store.py", "source_location": "L312"}, {"id": "ndarray", "label": "ndarray", "file_type": "code", "source_file": "sidecar/sidecar/store.py", "source_location": "L312"}, {"id": "sidecar_store_store_delete_many", "label": ".delete_many()", "file_type": "code", "source_file": "sidecar/sidecar/store.py", "source_location": "L397"}, {"id": "sidecar_store_store_count_vectors", "label": ".count_vectors()", "file_type": "code", "source_file": "sidecar/sidecar/store.py", "source_location": "L425"}, {"id": "sidecar_store_store_all_vector_ids", "label": ".all_vector_ids()", "file_type": "code", "source_file": "sidecar/sidecar/store.py", "source_location": "L432"}, {"id": "sidecar_store_store_active_model", "label": "._active_model()", "file_type": "code", "source_file": "sidecar/sidecar/store.py", "source_location": "L446"}, {"id": "sidecar_store_rationale_1", "label": "SQLite-backed embedding metadata store.  The store is the sidecar's source of tr", "file_type": "rationale", "source_file": "sidecar/sidecar/store.py", "source_location": "L1"}, {"id": "sidecar_store_rationale_67", "label": "A single ``tools`` row, decoded.      ``tags`` is a Python list (decoded from th", "file_type": "rationale", "source_file": "sidecar/sidecar/store.py", "source_location": "L67"}, {"id": "sidecar_store_rationale_107", "label": "SQLite-backed embedding metadata store.      The store owns its own connection (", "file_type": "rationale", "source_file": "sidecar/sidecar/store.py", "source_location": "L107"}, {"id": "sidecar_store_rationale_182", "label": "Return the meta value for ``key`` or None when missing.", "file_type": "rationale", "source_file": "sidecar/sidecar/store.py", "source_location": "L182"}, {"id": "sidecar_store_rationale_190", "label": "Insert-or-replace the meta value for ``key``.", "file_type": "rationale", "source_file": "sidecar/sidecar/store.py", "source_location": "L190"}, {"id": "sidecar_store_rationale_203", "label": "Return the row for ``tool_ref`` or None when missing.", "file_type": "rationale", "source_file": "sidecar/sidecar/store.py", "source_location": "L203"}, {"id": "sidecar_store_rationale_213", "label": "Return the row for ``vector_id`` or None when missing.", "file_type": "rationale", "source_file": "sidecar/sidecar/store.py", "source_location": "L213"}, {"id": "sidecar_store_rationale_223", "label": "Yield every tool row in insertion order of ``vector_id``.          Used by the r", "file_type": "rationale", "source_file": "sidecar/sidecar/store.py", "source_location": "L223"}, {"id": "sidecar_store_rationale_243", "label": "Return the matching ``vector_id``s for a facet filter.          Empty inputs mea", "file_type": "rationale", "source_file": "sidecar/sidecar/store.py", "source_location": "L243"}, {"id": "sidecar_store_rationale_284", "label": "Classify an upsert intent.          Returns one of:          - ``\"unchanged\"``:", "file_type": "rationale", "source_file": "sidecar/sidecar/store.py", "source_location": "L284"}, {"id": "sidecar_store_rationale_323", "label": "Persist one tool row.          Args:             tool_ref: Stable id of the tool", "file_type": "rationale", "source_file": "sidecar/sidecar/store.py", "source_location": "L323"}, {"id": "sidecar_store_rationale_398", "label": "Delete the named tools and return their former ``vector_id``s.          The retu", "file_type": "rationale", "source_file": "sidecar/sidecar/store.py", "source_location": "L398"}, {"id": "sidecar_store_rationale_426", "label": "Return the number of tools currently stored.", "file_type": "rationale", "source_file": "sidecar/sidecar/store.py", "source_location": "L426"}, {"id": "sidecar_store_rationale_433", "label": "Return every ``vector_id`` in ascending order.          Used by the rebuild path", "file_type": "rationale", "source_file": "sidecar/sidecar/store.py", "source_location": "L433"}, {"id": "sidecar_store_rationale_447", "label": "Return the active embedding model recorded in ``meta`` (if any).", "file_type": "rationale", "source_file": "sidecar/sidecar/store.py", "source_location": "L447"}], "edges": [{"source": "users_rokaskucinskas_development_ozy_sidecar_sidecar_store_py", "target": "json", "relation": "imports", "context": "import", "confidence": "EXTRACTED", "source_file": "sidecar/sidecar/store.py", "source_location": "L39", "weight": 1.0}, {"source": "users_rokaskucinskas_development_ozy_sidecar_sidecar_store_py", "target": "logging", "relation": "imports", "context": "import", "confidence": "EXTRACTED", "source_file": "sidecar/sidecar/store.py", "source_location": "L40", "weight": 1.0}, {"source": "users_rokaskucinskas_development_ozy_sidecar_sidecar_store_py", "target": "os", "relation": "imports", "context": "import", "confidence": "EXTRACTED", "source_file": "sidecar/sidecar/store.py", "source_location": "L41", "weight": 1.0}, {"source": "users_rokaskucinskas_development_ozy_sidecar_sidecar_store_py", "target": "sqlite3", "relation": "imports", "context": "import", "confidence": "EXTRACTED", "source_file": "sidecar/sidecar/store.py", "source_location": "L42", "weight": 1.0}, {"source": "users_rokaskucinskas_development_ozy_sidecar_sidecar_store_py", "target": "threading", "relation": "imports", "context": "import", "confidence": "EXTRACTED", "source_file": "sidecar/sidecar/store.py", "source_location": "L43", "weight": 1.0}, {"source": "users_rokaskucinskas_development_ozy_sidecar_sidecar_store_py", "target": "dataclasses", "relation": "imports_from", "context": "import", "confidence": "EXTRACTED", "source_file": "sidecar/sidecar/store.py", "source_location": "L44", "weight": 1.0}, {"source": "users_rokaskucinskas_development_ozy_sidecar_sidecar_store_py", "target": "typing", "relation": "imports_from", "context": "import", "confidence": "EXTRACTED", "source_file": "sidecar/sidecar/store.py", "source_location": "L45", "weight": 1.0}, {"source": "users_rokaskucinskas_development_ozy_sidecar_sidecar_store_py", "target": "numpy", "relation": "imports", "context": "import", "confidence": "EXTRACTED", "source_file": "sidecar/sidecar/store.py", "source_location": "L49", "weight": 1.0}, {"source": "users_rokaskucinskas_development_ozy_sidecar_sidecar_store_py", "target": "sidecar_store_toolrow", "relation": "contains", "confidence": "EXTRACTED", "source_file": "sidecar/sidecar/store.py", "source_location": "L66", "weight": 1.0}, {"source": "users_rokaskucinskas_development_ozy_sidecar_sidecar_store_py", "target": "sidecar_store_row_to_tool_row", "relation": "contains", "confidence": "EXTRACTED", "source_file": "sidecar/sidecar/store.py", "source_location": "L83", "weight": 1.0}, {"source": "sidecar_store_row_to_tool_row", "target": "row", "relation": "references", "context": "parameter_type", "confidence": "EXTRACTED", "source_file": "sidecar/sidecar/store.py", "source_location": "L83", "weight": 1.0}, {"source": "sidecar_store_row_to_tool_row", "target": "sidecar_store_toolrow", "relation": "references", "context": "return_type", "confidence": "EXTRACTED", "source_file": "sidecar/sidecar/store.py", "source_location": "L83", "weight": 1.0}, {"source": "users_rokaskucinskas_development_ozy_sidecar_sidecar_store_py", "target": "sidecar_store_store", "relation": "contains", "confidence": "EXTRACTED", "source_file": "sidecar/sidecar/store.py", "source_location": "L106", "weight": 1.0}, {"source": "sidecar_store_store", "target": "sidecar_store_store_init", "relation": "method", "confidence": "EXTRACTED", "source_file": "sidecar/sidecar/store.py", "source_location": "L116", "weight": 1.0}, {"source": "sidecar_store_store", "target": "sidecar_store_store_close", "relation": "method", "confidence": "EXTRACTED", "source_file": "sidecar/sidecar/store.py", "source_location": "L129", "weight": 1.0}, {"source": "sidecar_store_store", "target": "sidecar_store_store_enter", "relation": "method", "confidence": "EXTRACTED", "source_file": "sidecar/sidecar/store.py", "source_location": "L136", "weight": 1.0}, {"source": "sidecar_store_store", "target": "sidecar_store_store_exit", "relation": "method", "confidence": "EXTRACTED", "source_file": "sidecar/sidecar/store.py", "source_location": "L139", "weight": 1.0}, {"source": "sidecar_store_store", "target": "sidecar_store_store_init_schema", "relation": "method", "confidence": "EXTRACTED", "source_file": "sidecar/sidecar/store.py", "source_location": "L144", "weight": 1.0}, {"source": "sidecar_store_store", "target": "sidecar_store_store_get_meta", "relation": "method", "confidence": "EXTRACTED", "source_file": "sidecar/sidecar/store.py", "source_location": "L181", "weight": 1.0}, {"source": "sidecar_store_store", "target": "sidecar_store_store_set_meta", "relation": "method", "confidence": "EXTRACTED", "source_file": "sidecar/sidecar/store.py", "source_location": "L189", "weight": 1.0}, {"source": "sidecar_store_store", "target": "sidecar_store_store_get_by_toolref", "relation": "method", "confidence": "EXTRACTED", "source_file": "sidecar/sidecar/store.py", "source_location": "L202", "weight": 1.0}, {"source": "sidecar_store_store_get_by_toolref", "target": "sidecar_store_toolrow", "relation": "references", "context": "return_type", "confidence": "EXTRACTED", "source_file": "sidecar/sidecar/store.py", "source_location": "L202", "weight": 1.0}, {"source": "sidecar_store_store", "target": "sidecar_store_store_get_by_vector_id", "relation": "method", "confidence": "EXTRACTED", "source_file": "sidecar/sidecar/store.py", "source_location": "L212", "weight": 1.0}, {"source": "sidecar_store_store_get_by_vector_id", "target": "sidecar_store_toolrow", "relation": "references", "context": "return_type", "confidence": "EXTRACTED", "source_file": "sidecar/sidecar/store.py", "source_location": "L212", "weight": 1.0}, {"source": "sidecar_store_store", "target": "sidecar_store_store_iter_all", "relation": "method", "confidence": "EXTRACTED", "source_file": "sidecar/sidecar/store.py", "source_location": "L222", "weight": 1.0}, {"source": "sidecar_store_store_iter_all", "target": "sidecar_store_toolrow", "relation": "references", "context": "generic_arg", "confidence": "EXTRACTED", "source_file": "sidecar/sidecar/store.py", "source_location": "L222", "weight": 1.0}, {"source": "sidecar_store_store", "target": "sidecar_store_store_resolve_facet_allowlist", "relation": "method", "confidence": "EXTRACTED", "source_file": "sidecar/sidecar/store.py", "source_location": "L238", "weight": 1.0}, {"source": "sidecar_store_store", "target": "sidecar_store_store_compute_skip", "relation": "method", "confidence": "EXTRACTED", "source_file": "sidecar/sidecar/store.py", "source_location": "L281", "weight": 1.0}, {"source": "sidecar_store_store", "target": "sidecar_store_store_next_vector_id", "relation": "method", "confidence": "EXTRACTED", "source_file": "sidecar/sidecar/store.py", "source_location": "L304", "weight": 1.0}, {"source": "sidecar_store_store", "target": "sidecar_store_store_upsert_one", "relation": "method", "confidence": "EXTRACTED", "source_file": "sidecar/sidecar/store.py", "source_location": "L312", "weight": 1.0}, {"source": "sidecar_store_store_upsert_one", "target": "ndarray", "relation": "references", "context": "parameter_type", "confidence": "EXTRACTED", "source_file": "sidecar/sidecar/store.py", "source_location": "L312", "weight": 1.0}, {"source": "sidecar_store_store", "target": "sidecar_store_store_delete_many", "relation": "method", "confidence": "EXTRACTED", "source_file": "sidecar/sidecar/store.py", "source_location": "L397", "weight": 1.0}, {"source": "sidecar_store_store", "target": "sidecar_store_store_count_vectors", "relation": "method", "confidence": "EXTRACTED", "source_file": "sidecar/sidecar/store.py", "source_location": "L425", "weight": 1.0}, {"source": "sidecar_store_store", "target": "sidecar_store_store_all_vector_ids", "relation": "method", "confidence": "EXTRACTED", "source_file": "sidecar/sidecar/store.py", "source_location": "L432", "weight": 1.0}, {"source": "sidecar_store_store", "target": "sidecar_store_store_active_model", "relation": "method", "confidence": "EXTRACTED", "source_file": "sidecar/sidecar/store.py", "source_location": "L446", "weight": 1.0}, {"source": "sidecar_store_row_to_tool_row", "target": "sidecar_store_toolrow", "relation": "calls", "context": "call", "confidence": "EXTRACTED", "source_file": "sidecar/sidecar/store.py", "source_location": "L94", "weight": 1.0}, {"source": "sidecar_store_store_init", "target": "sidecar_store_store_init_schema", "relation": "calls", "context": "call", "confidence": "EXTRACTED", "source_file": "sidecar/sidecar/store.py", "source_location": "L127", "weight": 1.0}, {"source": "sidecar_store_store_exit", "target": "sidecar_store_store_close", "relation": "calls", "context": "call", "confidence": "EXTRACTED", "source_file": "sidecar/sidecar/store.py", "source_location": "L140", "weight": 1.0}, {"source": "sidecar_store_store_get_by_toolref", "target": "sidecar_store_row_to_tool_row", "relation": "calls", "context": "call", "confidence": "EXTRACTED", "source_file": "sidecar/sidecar/store.py", "source_location": "L210", "weight": 1.0}, {"source": "sidecar_store_store_get_by_vector_id", "target": "sidecar_store_row_to_tool_row", "relation": "calls", "context": "call", "confidence": "EXTRACTED", "source_file": "sidecar/sidecar/store.py", "source_location": "L220", "weight": 1.0}, {"source": "sidecar_store_store_iter_all", "target": "sidecar_store_row_to_tool_row", "relation": "calls", "context": "call", "confidence": "EXTRACTED", "source_file": "sidecar/sidecar/store.py", "source_location": "L236", "weight": 1.0}, {"source": "sidecar_store_store_compute_skip", "target": "sidecar_store_store_get_by_toolref", "relation": "calls", "context": "call", "confidence": "EXTRACTED", "source_file": "sidecar/sidecar/store.py", "source_location": "L297", "weight": 1.0}, {"source": "sidecar_store_store_upsert_one", "target": "sidecar_store_store_compute_skip", "relation": "calls", "context": "call", "confidence": "EXTRACTED", "source_file": "sidecar/sidecar/store.py", "source_location": "L344", "weight": 1.0}, {"source": "sidecar_store_store_upsert_one", "target": "sidecar_store_store_get_by_toolref", "relation": "calls", "context": "call", "confidence": "EXTRACTED", "source_file": "sidecar/sidecar/store.py", "source_location": "L346", "weight": 1.0}, {"source": "sidecar_store_store_upsert_one", "target": "sidecar_store_store_next_vector_id", "relation": "calls", "context": "call", "confidence": "EXTRACTED", "source_file": "sidecar/sidecar/store.py", "source_location": "L368", "weight": 1.0}, {"source": "sidecar_store_store_active_model", "target": "sidecar_store_store_get_meta", "relation": "calls", "context": "call", "confidence": "EXTRACTED", "source_file": "sidecar/sidecar/store.py", "source_location": "L449", "weight": 1.0}, {"source": "sidecar_store_rationale_1", "target": "users_rokaskucinskas_development_ozy_sidecar_sidecar_store_py", "relation": "rationale_for", "confidence": "EXTRACTED", "source_file": "sidecar/sidecar/store.py", "source_location": "L1", "weight": 1.0}, {"source": "sidecar_store_rationale_67", "target": "sidecar_store_toolrow", "relation": "rationale_for", "confidence": "EXTRACTED", "source_file": "sidecar/sidecar/store.py", "source_location": "L67", "weight": 1.0}, {"source": "sidecar_store_rationale_107", "target": "sidecar_store_store", "relation": "rationale_for", "confidence": "EXTRACTED", "source_file": "sidecar/sidecar/store.py", "source_location": "L107", "weight": 1.0}, {"source": "sidecar_store_rationale_182", "target": "sidecar_store_store_get_meta", "relation": "rationale_for", "confidence": "EXTRACTED", "source_file": "sidecar/sidecar/store.py", "source_location": "L182", "weight": 1.0}, {"source": "sidecar_store_rationale_190", "target": "sidecar_store_store_set_meta", "relation": "rationale_for", "confidence": "EXTRACTED", "source_file": "sidecar/sidecar/store.py", "source_location": "L190", "weight": 1.0}, {"source": "sidecar_store_rationale_203", "target": "sidecar_store_store_get_by_toolref", "relation": "rationale_for", "confidence": "EXTRACTED", "source_file": "sidecar/sidecar/store.py", "source_location": "L203", "weight": 1.0}, {"source": "sidecar_store_rationale_213", "target": "sidecar_store_store_get_by_vector_id", "relation": "rationale_for", "confidence": "EXTRACTED", "source_file": "sidecar/sidecar/store.py", "source_location": "L213", "weight": 1.0}, {"source": "sidecar_store_rationale_223", "target": "sidecar_store_store_iter_all", "relation": "rationale_for", "confidence": "EXTRACTED", "source_file": "sidecar/sidecar/store.py", "source_location": "L223", "weight": 1.0}, {"source": "sidecar_store_rationale_243", "target": "sidecar_store_store_resolve_facet_allowlist", "relation": "rationale_for", "confidence": "EXTRACTED", "source_file": "sidecar/sidecar/store.py", "source_location": "L243", "weight": 1.0}, {"source": "sidecar_store_rationale_284", "target": "sidecar_store_store_compute_skip", "relation": "rationale_for", "confidence": "EXTRACTED", "source_file": "sidecar/sidecar/store.py", "source_location": "L284", "weight": 1.0}, {"source": "sidecar_store_rationale_323", "target": "sidecar_store_store_upsert_one", "relation": "rationale_for", "confidence": "EXTRACTED", "source_file": "sidecar/sidecar/store.py", "source_location": "L323", "weight": 1.0}, {"source": "sidecar_store_rationale_398", "target": "sidecar_store_store_delete_many", "relation": "rationale_for", "confidence": "EXTRACTED", "source_file": "sidecar/sidecar/store.py", "source_location": "L398", "weight": 1.0}, {"source": "sidecar_store_rationale_426", "target": "sidecar_store_store_count_vectors", "relation": "rationale_for", "confidence": "EXTRACTED", "source_file": "sidecar/sidecar/store.py", "source_location": "L426", "weight": 1.0}, {"source": "sidecar_store_rationale_433", "target": "sidecar_store_store_all_vector_ids", "relation": "rationale_for", "confidence": "EXTRACTED", "source_file": "sidecar/sidecar/store.py", "source_location": "L433", "weight": 1.0}, {"source": "sidecar_store_rationale_447", "target": "sidecar_store_store_active_model", "relation": "rationale_for", "confidence": "EXTRACTED", "source_file": "sidecar/sidecar/store.py", "source_location": "L447", "weight": 1.0}], "raw_calls": [{"caller_nid": "sidecar_store_row_to_tool_row", "callee": "loads", "is_member_call": true, "source_file": "/Users/rokaskucinskas/Development/ozy/sidecar/sidecar/store.py", "source_location": "L86"}, {"caller_nid": "sidecar_store_row_to_tool_row", "callee": "copy", "is_member_call": true, "source_file": "/Users/rokaskucinskas/Development/ozy/sidecar/sidecar/store.py", "source_location": "L93"}, {"caller_nid": "sidecar_store_row_to_tool_row", "callee": "reshape", "is_member_call": true, "source_file": "/Users/rokaskucinskas/Development/ozy/sidecar/sidecar/store.py", "source_location": "L93"}, {"caller_nid": "sidecar_store_row_to_tool_row", "callee": "frombuffer", "is_member_call": true, "source_file": "/Users/rokaskucinskas/Development/ozy/sidecar/sidecar/store.py", "source_location": "L93"}, {"caller_nid": "sidecar_store_store_init", "callee": "makedirs", "is_member_call": true, "source_file": "/Users/rokaskucinskas/Development/ozy/sidecar/sidecar/store.py", "source_location": "L118"}, {"caller_nid": "sidecar_store_store_init", "callee": "dirname", "is_member_call": true, "source_file": "/Users/rokaskucinskas/Development/ozy/sidecar/sidecar/store.py", "source_location": "L118"}, {"caller_nid": "sidecar_store_store_init", "callee": "abspath", "is_member_call": true, "source_file": "/Users/rokaskucinskas/Development/ozy/sidecar/sidecar/store.py", "source_location": "L118"}, {"caller_nid": "sidecar_store_store_init", "callee": "RLock", "is_member_call": true, "source_file": "/Users/rokaskucinskas/Development/ozy/sidecar/sidecar/store.py", "source_location": "L119"}, {"caller_nid": "sidecar_store_store_init", "callee": "connect", "is_member_call": true, "source_file": "/Users/rokaskucinskas/Development/ozy/sidecar/sidecar/store.py", "source_location": "L120"}, {"caller_nid": "sidecar_store_store_init", "callee": "execute", "is_member_call": true, "source_file": "/Users/rokaskucinskas/Development/ozy/sidecar/sidecar/store.py", "source_location": "L124"}, {"caller_nid": "sidecar_store_store_init", "callee": "execute", "is_member_call": true, "source_file": "/Users/rokaskucinskas/Development/ozy/sidecar/sidecar/store.py", "source_location": "L125"}, {"caller_nid": "sidecar_store_store_init", "callee": "execute", "is_member_call": true, "source_file": "/Users/rokaskucinskas/Development/ozy/sidecar/sidecar/store.py", "source_location": "L126"}, {"caller_nid": "sidecar_store_store_init_schema", "callee": "executescript", "is_member_call": true, "source_file": "/Users/rokaskucinskas/Development/ozy/sidecar/sidecar/store.py", "source_location": "L146"}, {"caller_nid": "sidecar_store_store_init_schema", "callee": "execute", "is_member_call": true, "source_file": "/Users/rokaskucinskas/Development/ozy/sidecar/sidecar/store.py", "source_location": "L169"}, {"caller_nid": "sidecar_store_store_init_schema", "callee": "fetchone", "is_member_call": true, "source_file": "/Users/rokaskucinskas/Development/ozy/sidecar/sidecar/store.py", "source_location": "L172"}, {"caller_nid": "sidecar_store_store_init_schema", "callee": "execute", "is_member_call": true, "source_file": "/Users/rokaskucinskas/Development/ozy/sidecar/sidecar/store.py", "source_location": "L173"}, {"caller_nid": "sidecar_store_store_init_schema", "callee": "commit", "is_member_call": true, "source_file": "/Users/rokaskucinskas/Development/ozy/sidecar/sidecar/store.py", "source_location": "L177"}, {"caller_nid": "sidecar_store_store_get_meta", "callee": "execute", "is_member_call": true, "source_file": "/Users/rokaskucinskas/Development/ozy/sidecar/sidecar/store.py", "source_location": "L185"}, {"caller_nid": "sidecar_store_store_get_meta", "callee": "fetchone", "is_member_call": true, "source_file": "/Users/rokaskucinskas/Development/ozy/sidecar/sidecar/store.py", "source_location": "L186"}, {"caller_nid": "sidecar_store_store_set_meta", "callee": "execute", "is_member_call": true, "source_file": "/Users/rokaskucinskas/Development/ozy/sidecar/sidecar/store.py", "source_location": "L193"}, {"caller_nid": "sidecar_store_store_set_meta", "callee": "commit", "is_member_call": true, "source_file": "/Users/rokaskucinskas/Development/ozy/sidecar/sidecar/store.py", "source_location": "L198"}, {"caller_nid": "sidecar_store_store_get_by_toolref", "callee": "execute", "is_member_call": true, "source_file": "/Users/rokaskucinskas/Development/ozy/sidecar/sidecar/store.py", "source_location": "L206"}, {"caller_nid": "sidecar_store_store_get_by_toolref", "callee": "fetchone", "is_member_call": true, "source_file": "/Users/rokaskucinskas/Development/ozy/sidecar/sidecar/store.py", "source_location": "L209"}, {"caller_nid": "sidecar_store_store_get_by_vector_id", "callee": "execute", "is_member_call": true, "source_file": "/Users/rokaskucinskas/Development/ozy/sidecar/sidecar/store.py", "source_location": "L216"}, {"caller_nid": "sidecar_store_store_get_by_vector_id", "callee": "fetchone", "is_member_call": true, "source_file": "/Users/rokaskucinskas/Development/ozy/sidecar/sidecar/store.py", "source_location": "L219"}, {"caller_nid": "sidecar_store_store_iter_all", "callee": "execute", "is_member_call": true, "source_file": "/Users/rokaskucinskas/Development/ozy/sidecar/sidecar/store.py", "source_location": "L231"}, {"caller_nid": "sidecar_store_store_iter_all", "callee": "fetchall", "is_member_call": true, "source_file": "/Users/rokaskucinskas/Development/ozy/sidecar/sidecar/store.py", "source_location": "L234"}, {"caller_nid": "sidecar_store_store_resolve_facet_allowlist", "callee": "append", "is_member_call": true, "source_file": "/Users/rokaskucinskas/Development/ozy/sidecar/sidecar/store.py", "source_location": "L259"}, {"caller_nid": "sidecar_store_store_resolve_facet_allowlist", "callee": "append", "is_member_call": true, "source_file": "/Users/rokaskucinskas/Development/ozy/sidecar/sidecar/store.py", "source_location": "L260"}, {"caller_nid": "sidecar_store_store_resolve_facet_allowlist", "callee": "append", "is_member_call": true, "source_file": "/Users/rokaskucinskas/Development/ozy/sidecar/sidecar/store.py", "source_location": "L268"}, {"caller_nid": "sidecar_store_store_resolve_facet_allowlist", "callee": "append", "is_member_call": true, "source_file": "/Users/rokaskucinskas/Development/ozy/sidecar/sidecar/store.py", "source_location": "L269"}, {"caller_nid": "sidecar_store_store_resolve_facet_allowlist", "callee": "append", "is_member_call": true, "source_file": "/Users/rokaskucinskas/Development/ozy/sidecar/sidecar/store.py", "source_location": "L270"}, {"caller_nid": "sidecar_store_store_resolve_facet_allowlist", "callee": "join", "is_member_call": true, "source_file": "/Users/rokaskucinskas/Development/ozy/sidecar/sidecar/store.py", "source_location": "L270"}, {"caller_nid": "sidecar_store_store_resolve_facet_allowlist", "callee": "join", "is_member_call": true, "source_file": "/Users/rokaskucinskas/Development/ozy/sidecar/sidecar/store.py", "source_location": "L274"}, {"caller_nid": "sidecar_store_store_resolve_facet_allowlist", "callee": "execute", "is_member_call": true, "source_file": "/Users/rokaskucinskas/Development/ozy/sidecar/sidecar/store.py", "source_location": "L278"}, {"caller_nid": "sidecar_store_store_resolve_facet_allowlist", "callee": "fetchall", "is_member_call": true, "source_file": "/Users/rokaskucinskas/Development/ozy/sidecar/sidecar/store.py", "source_location": "L279"}, {"caller_nid": "sidecar_store_store_next_vector_id", "callee": "execute", "is_member_call": true, "source_file": "/Users/rokaskucinskas/Development/ozy/sidecar/sidecar/store.py", "source_location": "L306"}, {"caller_nid": "sidecar_store_store_next_vector_id", "callee": "fetchone", "is_member_call": true, "source_file": "/Users/rokaskucinskas/Development/ozy/sidecar/sidecar/store.py", "source_location": "L309"}, {"caller_nid": "sidecar_store_store_upsert_one", "callee": "asarray", "is_member_call": true, "source_file": "/Users/rokaskucinskas/Development/ozy/sidecar/sidecar/store.py", "source_location": "L350"}, {"caller_nid": "sidecar_store_store_upsert_one", "callee": "ValueError", "is_member_call": false, "source_file": "/Users/rokaskucinskas/Development/ozy/sidecar/sidecar/store.py", "source_location": "L352"}, {"caller_nid": "sidecar_store_store_upsert_one", "callee": "dumps", "is_member_call": true, "source_file": "/Users/rokaskucinskas/Development/ozy/sidecar/sidecar/store.py", "source_location": "L358"}, {"caller_nid": "sidecar_store_store_upsert_one", "callee": "execute", "is_member_call": true, "source_file": "/Users/rokaskucinskas/Development/ozy/sidecar/sidecar/store.py", "source_location": "L361"}, {"caller_nid": "sidecar_store_store_upsert_one", "callee": "fetchone", "is_member_call": true, "source_file": "/Users/rokaskucinskas/Development/ozy/sidecar/sidecar/store.py", "source_location": "L364"}, {"caller_nid": "sidecar_store_store_upsert_one", "callee": "execute", "is_member_call": true, "source_file": "/Users/rokaskucinskas/Development/ozy/sidecar/sidecar/store.py", "source_location": "L369"}, {"caller_nid": "sidecar_store_store_upsert_one", "callee": "tobytes", "is_member_call": true, "source_file": "/Users/rokaskucinskas/Development/ozy/sidecar/sidecar/store.py", "source_location": "L391"}, {"caller_nid": "sidecar_store_store_upsert_one", "callee": "commit", "is_member_call": true, "source_file": "/Users/rokaskucinskas/Development/ozy/sidecar/sidecar/store.py", "source_location": "L394"}, {"caller_nid": "sidecar_store_store_delete_many", "callee": "join", "is_member_call": true, "source_file": "/Users/rokaskucinskas/Development/ozy/sidecar/sidecar/store.py", "source_location": "L410"}, {"caller_nid": "sidecar_store_store_delete_many", "callee": "execute", "is_member_call": true, "source_file": "/Users/rokaskucinskas/Development/ozy/sidecar/sidecar/store.py", "source_location": "L414"}, {"caller_nid": "sidecar_store_store_delete_many", "callee": "fetchall", "is_member_call": true, "source_file": "/Users/rokaskucinskas/Development/ozy/sidecar/sidecar/store.py", "source_location": "L418"}, {"caller_nid": "sidecar_store_store_delete_many", "callee": "execute", "is_member_call": true, "source_file": "/Users/rokaskucinskas/Development/ozy/sidecar/sidecar/store.py", "source_location": "L419"}, {"caller_nid": "sidecar_store_store_delete_many", "callee": "commit", "is_member_call": true, "source_file": "/Users/rokaskucinskas/Development/ozy/sidecar/sidecar/store.py", "source_location": "L422"}, {"caller_nid": "sidecar_store_store_count_vectors", "callee": "execute", "is_member_call": true, "source_file": "/Users/rokaskucinskas/Development/ozy/sidecar/sidecar/store.py", "source_location": "L429"}, {"caller_nid": "sidecar_store_store_count_vectors", "callee": "fetchone", "is_member_call": true, "source_file": "/Users/rokaskucinskas/Development/ozy/sidecar/sidecar/store.py", "source_location": "L430"}, {"caller_nid": "sidecar_store_store_all_vector_ids", "callee": "execute", "is_member_call": true, "source_file": "/Users/rokaskucinskas/Development/ozy/sidecar/sidecar/store.py", "source_location": "L440"}, {"caller_nid": "sidecar_store_store_all_vector_ids", "callee": "fetchall", "is_member_call": true, "source_file": "/Users/rokaskucinskas/Development/ozy/sidecar/sidecar/store.py", "source_location": "L441"}]}