{"nodes": [{"id": "users_rokaskucinskas_development_ozy_sidecar_tests_conftest_py", "label": "conftest.py", "file_type": "code", "source_file": "sidecar/tests/conftest.py", "source_location": "L1"}, {"id": "tests_conftest_data_dir", "label": "data_dir()", "file_type": "code", "source_file": "sidecar/tests/conftest.py", "source_location": "L30"}, {"id": "path", "label": "Path", "file_type": "code", "source_file": "sidecar/tests/conftest.py", "source_location": "L30"}, {"id": "tests_conftest_fake_embedder", "label": "fake_embedder()", "file_type": "code", "source_file": "sidecar/tests/conftest.py", "source_location": "L42"}, {"id": "fakeembedder", "label": "FakeEmbedder", "file_type": "code", "source_file": "sidecar/tests/conftest.py", "source_location": "L42"}, {"id": "tests_conftest_small_embedder", "label": "small_embedder()", "file_type": "code", "source_file": "sidecar/tests/conftest.py", "source_location": "L53"}, {"id": "tests_conftest_store", "label": "store()", "file_type": "code", "source_file": "sidecar/tests/conftest.py", "source_location": "L64"}, {"id": "tests_conftest_turbovec_backend", "label": "turbovec_backend()", "file_type": "code", "source_file": "sidecar/tests/conftest.py", "source_location": "L76"}, {"id": "turbovecbackend", "label": "TurbovecBackend", "file_type": "code", "source_file": "sidecar/tests/conftest.py", "source_location": "L76"}, {"id": "tests_conftest_ops", "label": "ops()", "file_type": "code", "source_file": "sidecar/tests/conftest.py", "source_location": "L87"}, {"id": "tests_conftest_rationale_1", "label": "Shared pytest fixtures for the Ozy embedding sidecar tests.  Every test gets a f", "file_type": "rationale", "source_file": "sidecar/tests/conftest.py", "source_location": "L1"}, {"id": "tests_conftest_rationale_31", "label": "A fresh data dir for one test.      Returned as a string because that's the type", "file_type": "rationale", "source_file": "sidecar/tests/conftest.py", "source_location": "L31"}, {"id": "tests_conftest_rationale_43", "label": "A deterministic embedder with the BGE-small default dim.      Query and document", "file_type": "rationale", "source_file": "sidecar/tests/conftest.py", "source_location": "L43"}, {"id": "tests_conftest_rationale_54", "label": "A tiny-dim FakeEmbedder for vector backend tests.      Using a small dim keeps t", "file_type": "rationale", "source_file": "sidecar/tests/conftest.py", "source_location": "L54"}, {"id": "tests_conftest_rationale_65", "label": "A :class:`Store` rooted in ``data_dir``; closed at teardown.", "file_type": "rationale", "source_file": "sidecar/tests/conftest.py", "source_location": "L65"}, {"id": "tests_conftest_rationale_77", "label": "A turbovec backend at the test dim.      Tests that need a FAISS backend constru", "file_type": "rationale", "source_file": "sidecar/tests/conftest.py", "source_location": "L77"}, {"id": "tests_conftest_rationale_92", "label": "A wired :class:`Ops` with a turbovec backend and the fake embedder.      Mirrors", "file_type": "rationale", "source_file": "sidecar/tests/conftest.py", "source_location": "L92"}], "edges": [{"source": "users_rokaskucinskas_development_ozy_sidecar_tests_conftest_py", "target": "os", "relation": "imports", "context": "import", "confidence": "EXTRACTED", "source_file": "sidecar/tests/conftest.py", "source_location": "L10", "weight": 1.0}, {"source": "users_rokaskucinskas_development_ozy_sidecar_tests_conftest_py", "target": "sys", "relation": "imports", "context": "import", "confidence": "EXTRACTED", "source_file": "sidecar/tests/conftest.py", "source_location": "L11", "weight": 1.0}, {"source": "users_rokaskucinskas_development_ozy_sidecar_tests_conftest_py", "target": "pathlib", "relation": "imports_from", "context": "import", "confidence": "EXTRACTED", "source_file": "sidecar/tests/conftest.py", "source_location": "L12", "weight": 1.0}, {"source": "users_rokaskucinskas_development_ozy_sidecar_tests_conftest_py", "target": "typing", "relation": "imports_from", "context": "import", "confidence": "EXTRACTED", "source_file": "sidecar/tests/conftest.py", "source_location": "L13", "weight": 1.0}, {"source": "users_rokaskucinskas_development_ozy_sidecar_tests_conftest_py", "target": "pytest", "relation": "imports", "context": "import", "confidence": "EXTRACTED", "source_file": "sidecar/tests/conftest.py", "source_location": "L15", "weight": 1.0}, {"source": "users_rokaskucinskas_development_ozy_sidecar_tests_conftest_py", "target": "sidecar_embedder", "relation": "imports_from", "context": "import", "confidence": "EXTRACTED", "source_file": "sidecar/tests/conftest.py", "source_location": "L23", "weight": 1.0}, {"source": "users_rokaskucinskas_development_ozy_sidecar_tests_conftest_py", "target": "sidecar_ops", "relation": "imports_from", "context": "import", "confidence": "EXTRACTED", "source_file": "sidecar/tests/conftest.py", "source_location": "L24", "weight": 1.0}, {"source": "users_rokaskucinskas_development_ozy_sidecar_tests_conftest_py", "target": "sidecar_store", "relation": "imports_from", "context": "import", "confidence": "EXTRACTED", "source_file": "sidecar/tests/conftest.py", "source_location": "L25", "weight": 1.0}, {"source": "users_rokaskucinskas_development_ozy_sidecar_tests_conftest_py", "target": "sidecar_vector", "relation": "imports_from", "context": "import", "confidence": "EXTRACTED", "source_file": "sidecar/tests/conftest.py", "source_location": "L26", "weight": 1.0}, {"source": "users_rokaskucinskas_development_ozy_sidecar_tests_conftest_py", "target": "tests_conftest_data_dir", "relation": "contains", "confidence": "EXTRACTED", "source_file": "sidecar/tests/conftest.py", "source_location": "L30", "weight": 1.0}, {"source": "tests_conftest_data_dir", "target": "path", "relation": "references", "context": "parameter_type", "confidence": "EXTRACTED", "source_file": "sidecar/tests/conftest.py", "source_location": "L30", "weight": 1.0}, {"source": "users_rokaskucinskas_development_ozy_sidecar_tests_conftest_py", "target": "tests_conftest_fake_embedder", "relation": "contains", "confidence": "EXTRACTED", "source_file": "sidecar/tests/conftest.py", "source_location": "L42", "weight": 1.0}, {"source": "tests_conftest_fake_embedder", "target": "fakeembedder", "relation": "references", "context": "return_type", "confidence": "EXTRACTED", "source_file": "sidecar/tests/conftest.py", "source_location": "L42", "weight": 1.0}, {"source": "users_rokaskucinskas_development_ozy_sidecar_tests_conftest_py", "target": "tests_conftest_small_embedder", "relation": "contains", "confidence": "EXTRACTED", "source_file": "sidecar/tests/conftest.py", "source_location": "L53", "weight": 1.0}, {"source": "tests_conftest_small_embedder", "target": "fakeembedder", "relation": "references", "context": "return_type", "confidence": "EXTRACTED", "source_file": "sidecar/tests/conftest.py", "source_location": "L53", "weight": 1.0}, {"source": "users_rokaskucinskas_development_ozy_sidecar_tests_conftest_py", "target": "tests_conftest_store", "relation": "contains", "confidence": "EXTRACTED", "source_file": "sidecar/tests/conftest.py", "source_location": "L64", "weight": 1.0}, {"source": "users_rokaskucinskas_development_ozy_sidecar_tests_conftest_py", "target": "tests_conftest_turbovec_backend", "relation": "contains", "confidence": "EXTRACTED", "source_file": "sidecar/tests/conftest.py", "source_location": "L76", "weight": 1.0}, {"source": "tests_conftest_turbovec_backend", "target": "fakeembedder", "relation": "references", "context": "parameter_type", "confidence": "EXTRACTED", "source_file": "sidecar/tests/conftest.py", "source_location": "L76", "weight": 1.0}, {"source": "tests_conftest_turbovec_backend", "target": "turbovecbackend", "relation": "references", "context": "return_type", "confidence": "EXTRACTED", "source_file": "sidecar/tests/conftest.py", "source_location": "L76", "weight": 1.0}, {"source": "users_rokaskucinskas_development_ozy_sidecar_tests_conftest_py", "target": "tests_conftest_ops", "relation": "contains", "confidence": "EXTRACTED", "source_file": "sidecar/tests/conftest.py", "source_location": "L87", "weight": 1.0}, {"source": "tests_conftest_ops", "target": "fakeembedder", "relation": "references", "context": "parameter_type", "confidence": "EXTRACTED", "source_file": "sidecar/tests/conftest.py", "source_location": "L87", "weight": 1.0}, {"source": "tests_conftest_ops", "target": "tests_conftest_store", "relation": "references", "context": "parameter_type", "confidence": "EXTRACTED", "source_file": "sidecar/tests/conftest.py", "source_location": "L87", "weight": 1.0}, {"source": "tests_conftest_fake_embedder", "target": "fakeembedder", "relation": "calls", "context": "call", "confidence": "EXTRACTED", "source_file": "sidecar/tests/conftest.py", "source_location": "L49", "weight": 1.0}, {"source": "tests_conftest_small_embedder", "target": "fakeembedder", "relation": "calls", "context": "call", "confidence": "EXTRACTED", "source_file": "sidecar/tests/conftest.py", "source_location": "L60", "weight": 1.0}, {"source": "tests_conftest_turbovec_backend", "target": "turbovecbackend", "relation": "calls", "context": "call", "confidence": "EXTRACTED", "source_file": "sidecar/tests/conftest.py", "source_location": "L83", "weight": 1.0}, {"source": "tests_conftest_ops", "target": "turbovecbackend", "relation": "calls", "context": "call", "confidence": "EXTRACTED", "source_file": "sidecar/tests/conftest.py", "source_location": "L100", "weight": 1.0}, {"source": "tests_conftest_rationale_1", "target": "users_rokaskucinskas_development_ozy_sidecar_tests_conftest_py", "relation": "rationale_for", "confidence": "EXTRACTED", "source_file": "sidecar/tests/conftest.py", "source_location": "L1", "weight": 1.0}, {"source": "tests_conftest_rationale_31", "target": "tests_conftest_data_dir", "relation": "rationale_for", "confidence": "EXTRACTED", "source_file": "sidecar/tests/conftest.py", "source_location": "L31", "weight": 1.0}, {"source": "tests_conftest_rationale_43", "target": "tests_conftest_fake_embedder", "relation": "rationale_for", "confidence": "EXTRACTED", "source_file": "sidecar/tests/conftest.py", "source_location": "L43", "weight": 1.0}, {"source": "tests_conftest_rationale_54", "target": "tests_conftest_small_embedder", "relation": "rationale_for", "confidence": "EXTRACTED", "source_file": "sidecar/tests/conftest.py", "source_location": "L54", "weight": 1.0}, {"source": "tests_conftest_rationale_65", "target": "tests_conftest_store", "relation": "rationale_for", "confidence": "EXTRACTED", "source_file": "sidecar/tests/conftest.py", "source_location": "L65", "weight": 1.0}, {"source": "tests_conftest_rationale_77", "target": "tests_conftest_turbovec_backend", "relation": "rationale_for", "confidence": "EXTRACTED", "source_file": "sidecar/tests/conftest.py", "source_location": "L77", "weight": 1.0}, {"source": "tests_conftest_rationale_92", "target": "tests_conftest_ops", "relation": "rationale_for", "confidence": "EXTRACTED", "source_file": "sidecar/tests/conftest.py", "source_location": "L92", "weight": 1.0}], "raw_calls": [{"caller_nid": "tests_conftest_store", "callee": "join", "is_member_call": true, "source_file": "/Users/rokaskucinskas/Development/ozy/sidecar/tests/conftest.py", "source_location": "L67"}, {"caller_nid": "tests_conftest_store", "callee": "Store", "is_member_call": false, "source_file": "/Users/rokaskucinskas/Development/ozy/sidecar/tests/conftest.py", "source_location": "L68"}, {"caller_nid": "tests_conftest_store", "callee": "close", "is_member_call": true, "source_file": "/Users/rokaskucinskas/Development/ozy/sidecar/tests/conftest.py", "source_location": "L72"}, {"caller_nid": "tests_conftest_ops", "callee": "Ops", "is_member_call": false, "source_file": "/Users/rokaskucinskas/Development/ozy/sidecar/tests/conftest.py", "source_location": "L101"}, {"caller_nid": "tests_conftest_ops", "callee": "close", "is_member_call": true, "source_file": "/Users/rokaskucinskas/Development/ozy/sidecar/tests/conftest.py", "source_location": "L111"}]}