{"nodes": [{"id": "users_rokaskucinskas_development_ozy_internal_installer_steps_go", "label": "steps.go", "file_type": "code", "source_file": "internal/installer/steps.go", "source_location": "L1"}, {"id": "installer_step", "label": "step", "file_type": "code", "source_file": "internal/installer/steps.go", "source_location": "L22"}, {"id": "risk", "label": "Risk", "file_type": "code", "source_file": "internal/installer/steps.go", "source_location": "L29"}, {"id": "execcontext", "label": "execContext", "file_type": "code", "source_file": "internal/installer/steps.go", "source_location": "L30"}, {"id": "installer_execcontext", "label": "execContext", "file_type": "code", "source_file": "internal/installer/steps.go", "source_location": "L36"}, {"id": "context", "label": "Context", "file_type": "code", "source_file": "internal/installer/steps.go", "source_location": "L37"}, {"id": "plan", "label": "Plan", "file_type": "code", "source_file": "internal/installer/steps.go", "source_location": "L38"}, {"id": "paths", "label": "Paths", "file_type": "code", "source_file": "internal/installer/steps.go", "source_location": "L39"}, {"id": "logger", "label": "Logger", "file_type": "code", "source_file": "internal/installer/steps.go", "source_location": "L40"}, {"id": "consentpolicy", "label": "ConsentPolicy", "file_type": "code", "source_file": "internal/installer/steps.go", "source_location": "L41"}, {"id": "reader", "label": "Reader", "file_type": "code", "source_file": "internal/installer/steps.go", "source_location": "L42"}, {"id": "writer", "label": "Writer", "file_type": "code", "source_file": "internal/installer/steps.go", "source_location": "L43"}, {"id": "runner", "label": "runner", "file_type": "code", "source_file": "internal/installer/steps.go", "source_location": "L44"}, {"id": "progress", "label": "Progress", "file_type": "code", "source_file": "internal/installer/steps.go", "source_location": "L45"}, {"id": "state", "label": "State", "file_type": "code", "source_file": "internal/installer/steps.go", "source_location": "L46"}, {"id": "statestore", "label": "StateStore", "file_type": "code", "source_file": "internal/installer/steps.go", "source_location": "L47"}, {"id": "installer_execcontext_allow", "label": ".allow()", "file_type": "code", "source_file": "internal/installer/steps.go", "source_location": "L57"}, {"id": "installer_execcontext_execute", "label": ".execute()", "file_type": "code", "source_file": "internal/installer/steps.go", "source_location": "L64"}, {"id": "installer_steps_installsteps", "label": "installSteps()", "file_type": "code", "source_file": "internal/installer/steps.go", "source_location": "L94"}, {"id": "installer_steps_stepnames", "label": "stepNames()", "file_type": "code", "source_file": "internal/installer/steps.go", "source_location": "L164"}, {"id": "installer_steps_stepdetectplatform", "label": "stepDetectPlatform()", "file_type": "code", "source_file": "internal/installer/steps.go", "source_location": "L175"}, {"id": "installer_steps_stepresolveinstalldirs", "label": "stepResolveInstallDirs()", "file_type": "code", "source_file": "internal/installer/steps.go", "source_location": "L180"}, {"id": "installer_steps_stepcheckexistinginstall", "label": "stepCheckExistingInstall()", "file_type": "code", "source_file": "internal/installer/steps.go", "source_location": "L185"}, {"id": "installer_steps_stepcheckdependencies", "label": "stepCheckDependencies()", "file_type": "code", "source_file": "internal/installer/steps.go", "source_location": "L194"}, {"id": "installer_steps_installdirs", "label": "installDirs()", "file_type": "code", "source_file": "internal/installer/steps.go", "source_location": "L208"}, {"id": "installer_steps_stepcreateinstallroot", "label": "stepCreateInstallRoot()", "file_type": "code", "source_file": "internal/installer/steps.go", "source_location": "L212"}, {"id": "installer_steps_validinstallroot", "label": "validInstallRoot()", "file_type": "code", "source_file": "internal/installer/steps.go", "source_location": "L221"}, {"id": "installer_steps_stepinstallozybinary", "label": "stepInstallOzyBinary()", "file_type": "code", "source_file": "internal/installer/steps.go", "source_location": "L230"}, {"id": "installer_steps_validbinary", "label": "validBinary()", "file_type": "code", "source_file": "internal/installer/steps.go", "source_location": "L254"}, {"id": "installer_steps_installref", "label": "installRef()", "file_type": "code", "source_file": "internal/installer/steps.go", "source_location": "L259"}, {"id": "installer_steps_stepcreateorupdateconfig", "label": "stepCreateOrUpdateConfig()", "file_type": "code", "source_file": "internal/installer/steps.go", "source_location": "L266"}, {"id": "installer_steps_validconfig", "label": "validConfig()", "file_type": "code", "source_file": "internal/installer/steps.go", "source_location": "L270"}, {"id": "installer_steps_stepsetuppythonenvironment", "label": "stepSetupPythonEnvironment()", "file_type": "code", "source_file": "internal/installer/steps.go", "source_location": "L278"}, {"id": "installer_steps_stepdownloadembeddingassets", "label": "stepDownloadEmbeddingAssets()", "file_type": "code", "source_file": "internal/installer/steps.go", "source_location": "L305"}, {"id": "installer_steps_stepbuildorloadtoolcatalog", "label": "stepBuildOrLoadToolCatalog()", "file_type": "code", "source_file": "internal/installer/steps.go", "source_location": "L317"}, {"id": "installer_steps_steprundoctor", "label": "stepRunDoctor()", "file_type": "code", "source_file": "internal/installer/steps.go", "source_location": "L328"}, {"id": "installer_steps_stepprintnextsteps", "label": "stepPrintNextSteps()", "file_type": "code", "source_file": "internal/installer/steps.go", "source_location": "L341"}, {"id": "installer_steps_boollabel", "label": "boolLabel()", "file_type": "code", "source_file": "internal/installer/steps.go", "source_location": "L373"}, {"id": "installer_steps_direxists", "label": "dirExists()", "file_type": "code", "source_file": "internal/installer/steps.go", "source_location": "L380"}], "edges": [{"source": "users_rokaskucinskas_development_ozy_internal_installer_steps_go", "target": "go_pkg_context", "relation": "imports_from", "confidence": "EXTRACTED", "source_file": "internal/installer/steps.go", "source_location": "L4", "weight": 1.0, "context": "import"}, {"source": "users_rokaskucinskas_development_ozy_internal_installer_steps_go", "target": "go_pkg_errors", "relation": "imports_from", "confidence": "EXTRACTED", "source_file": "internal/installer/steps.go", "source_location": "L5", "weight": 1.0, "context": "import"}, {"source": "users_rokaskucinskas_development_ozy_internal_installer_steps_go", "target": "go_pkg_fmt", "relation": "imports_from", "confidence": "EXTRACTED", "source_file": "internal/installer/steps.go", "source_location": "L6", "weight": 1.0, "context": "import"}, {"source": "users_rokaskucinskas_development_ozy_internal_installer_steps_go", "target": "go_pkg_io", "relation": "imports_from", "confidence": "EXTRACTED", "source_file": "internal/installer/steps.go", "source_location": "L7", "weight": 1.0, "context": "import"}, {"source": "users_rokaskucinskas_development_ozy_internal_installer_steps_go", "target": "go_pkg_os", "relation": "imports_from", "confidence": "EXTRACTED", "source_file": "internal/installer/steps.go", "source_location": "L8", "weight": 1.0, "context": "import"}, {"source": "users_rokaskucinskas_development_ozy_internal_installer_steps_go", "target": "go_pkg_path_filepath", "relation": "imports_from", "confidence": "EXTRACTED", "source_file": "internal/installer/steps.go", "source_location": "L9", "weight": 1.0, "context": "import"}, {"source": "users_rokaskucinskas_development_ozy_internal_installer_steps_go", "target": "go_pkg_strings", "relation": "imports_from", "confidence": "EXTRACTED", "source_file": "internal/installer/steps.go", "source_location": "L10", "weight": 1.0, "context": "import"}, {"source": "users_rokaskucinskas_development_ozy_internal_installer_steps_go", "target": "go_pkg_github_com_rokasklive_ozy_internal_catalog", "relation": "imports_from", "confidence": "EXTRACTED", "source_file": "internal/installer/steps.go", "source_location": "L12", "weight": 1.0, "context": "import"}, {"source": "users_rokaskucinskas_development_ozy_internal_installer_steps_go", "target": "go_pkg_github_com_rokasklive_ozy_internal_config", "relation": "imports_from", "confidence": "EXTRACTED", "source_file": "internal/installer/steps.go", "source_location": "L13", "weight": 1.0, "context": "import"}, {"source": "users_rokaskucinskas_development_ozy_internal_installer_steps_go", "target": "go_pkg_github_com_rokasklive_ozy_internal_paths", "relation": "imports_from", "confidence": "EXTRACTED", "source_file": "internal/installer/steps.go", "source_location": "L14", "weight": 1.0, "context": "import"}, {"source": "users_rokaskucinskas_development_ozy_internal_installer_steps_go", "target": "go_pkg_github_com_rokasklive_ozy_internal_sidecar", "relation": "imports_from", "confidence": "EXTRACTED", "source_file": "internal/installer/steps.go", "source_location": "L15", "weight": 1.0, "context": "import"}, {"source": "users_rokaskucinskas_development_ozy_internal_installer_steps_go", "target": "installer_step", "relation": "contains", "confidence": "EXTRACTED", "source_file": "internal/installer/steps.go", "source_location": "L22", "weight": 1.0}, {"source": "installer_step", "target": "risk", "relation": "references", "confidence": "EXTRACTED", "source_file": "internal/installer/steps.go", "source_location": "L29", "weight": 1.0, "context": "field"}, {"source": "installer_step", "target": "execcontext", "relation": "references", "confidence": "EXTRACTED", "source_file": "internal/installer/steps.go", "source_location": "L30", "weight": 1.0, "context": "field"}, {"source": "installer_step", "target": "execcontext", "relation": "references", "confidence": "EXTRACTED", "source_file": "internal/installer/steps.go", "source_location": "L31", "weight": 1.0, "context": "field"}, {"source": "users_rokaskucinskas_development_ozy_internal_installer_steps_go", "target": "installer_execcontext", "relation": "contains", "confidence": "EXTRACTED", "source_file": "internal/installer/steps.go", "source_location": "L36", "weight": 1.0}, {"source": "installer_execcontext", "target": "context", "relation": "references", "confidence": "EXTRACTED", "source_file": "internal/installer/steps.go", "source_location": "L37", "weight": 1.0, "context": "field"}, {"source": "installer_execcontext", "target": "plan", "relation": "references", "confidence": "EXTRACTED", "source_file": "internal/installer/steps.go", "source_location": "L38", "weight": 1.0, "context": "field"}, {"source": "installer_execcontext", "target": "paths", "relation": "references", "confidence": "EXTRACTED", "source_file": "internal/installer/steps.go", "source_location": "L39", "weight": 1.0, "context": "field"}, {"source": "installer_execcontext", "target": "logger", "relation": "references", "confidence": "EXTRACTED", "source_file": "internal/installer/steps.go", "source_location": "L40", "weight": 1.0, "context": "field"}, {"source": "installer_execcontext", "target": "consentpolicy", "relation": "references", "confidence": "EXTRACTED", "source_file": "internal/installer/steps.go", "source_location": "L41", "weight": 1.0, "context": "field"}, {"source": "installer_execcontext", "target": "reader", "relation": "references", "confidence": "EXTRACTED", "source_file": "internal/installer/steps.go", "source_location": "L42", "weight": 1.0, "context": "field"}, {"source": "installer_execcontext", "target": "writer", "relation": "references", "confidence": "EXTRACTED", "source_file": "internal/installer/steps.go", "source_location": "L43", "weight": 1.0, "context": "field"}, {"source": "installer_execcontext", "target": "runner", "relation": "references", "confidence": "EXTRACTED", "source_file": "internal/installer/steps.go", "source_location": "L44", "weight": 1.0, "context": "field"}, {"source": "installer_execcontext", "target": "progress", "relation": "references", "confidence": "EXTRACTED", "source_file": "internal/installer/steps.go", "source_location": "L45", "weight": 1.0, "context": "field"}, {"source": "installer_execcontext", "target": "state", "relation": "references", "confidence": "EXTRACTED", "source_file": "internal/installer/steps.go", "source_location": "L46", "weight": 1.0, "context": "field"}, {"source": "installer_execcontext", "target": "statestore", "relation": "references", "confidence": "EXTRACTED", "source_file": "internal/installer/steps.go", "source_location": "L47", "weight": 1.0, "context": "field"}, {"source": "installer_execcontext", "target": "installer_execcontext_allow", "relation": "method", "confidence": "EXTRACTED", "source_file": "internal/installer/steps.go", "source_location": "L57", "weight": 1.0}, {"source": "installer_execcontext_allow", "target": "risk", "relation": "references", "confidence": "EXTRACTED", "source_file": "internal/installer/steps.go", "source_location": "L57", "weight": 1.0, "context": "parameter_type"}, {"source": "installer_execcontext", "target": "installer_execcontext_execute", "relation": "method", "confidence": "EXTRACTED", "source_file": "internal/installer/steps.go", "source_location": "L64", "weight": 1.0}, {"source": "installer_execcontext_execute", "target": "installer_step", "relation": "references", "confidence": "EXTRACTED", "source_file": "internal/installer/steps.go", "source_location": "L64", "weight": 1.0, "context": "parameter_type"}, {"source": "users_rokaskucinskas_development_ozy_internal_installer_steps_go", "target": "installer_steps_installsteps", "relation": "contains", "confidence": "EXTRACTED", "source_file": "internal/installer/steps.go", "source_location": "L94", "weight": 1.0}, {"source": "installer_steps_installsteps", "target": "installer_step", "relation": "references", "confidence": "EXTRACTED", "source_file": "internal/installer/steps.go", "source_location": "L94", "weight": 1.0, "context": "return_type"}, {"source": "users_rokaskucinskas_development_ozy_internal_installer_steps_go", "target": "installer_steps_stepnames", "relation": "contains", "confidence": "EXTRACTED", "source_file": "internal/installer/steps.go", "source_location": "L164", "weight": 1.0}, {"source": "users_rokaskucinskas_development_ozy_internal_installer_steps_go", "target": "installer_steps_stepdetectplatform", "relation": "contains", "confidence": "EXTRACTED", "source_file": "internal/installer/steps.go", "source_location": "L175", "weight": 1.0}, {"source": "installer_steps_stepdetectplatform", "target": "installer_execcontext", "relation": "references", "confidence": "EXTRACTED", "source_file": "internal/installer/steps.go", "source_location": "L175", "weight": 1.0, "context": "parameter_type"}, {"source": "users_rokaskucinskas_development_ozy_internal_installer_steps_go", "target": "installer_steps_stepresolveinstalldirs", "relation": "contains", "confidence": "EXTRACTED", "source_file": "internal/installer/steps.go", "source_location": "L180", "weight": 1.0}, {"source": "installer_steps_stepresolveinstalldirs", "target": "installer_execcontext", "relation": "references", "confidence": "EXTRACTED", "source_file": "internal/installer/steps.go", "source_location": "L180", "weight": 1.0, "context": "parameter_type"}, {"source": "users_rokaskucinskas_development_ozy_internal_installer_steps_go", "target": "installer_steps_stepcheckexistinginstall", "relation": "contains", "confidence": "EXTRACTED", "source_file": "internal/installer/steps.go", "source_location": "L185", "weight": 1.0}, {"source": "installer_steps_stepcheckexistinginstall", "target": "installer_execcontext", "relation": "references", "confidence": "EXTRACTED", "source_file": "internal/installer/steps.go", "source_location": "L185", "weight": 1.0, "context": "parameter_type"}, {"source": "users_rokaskucinskas_development_ozy_internal_installer_steps_go", "target": "installer_steps_stepcheckdependencies", "relation": "contains", "confidence": "EXTRACTED", "source_file": "internal/installer/steps.go", "source_location": "L194", "weight": 1.0}, {"source": "installer_steps_stepcheckdependencies", "target": "installer_execcontext", "relation": "references", "confidence": "EXTRACTED", "source_file": "internal/installer/steps.go", "source_location": "L194", "weight": 1.0, "context": "parameter_type"}, {"source": "users_rokaskucinskas_development_ozy_internal_installer_steps_go", "target": "installer_steps_installdirs", "relation": "contains", "confidence": "EXTRACTED", "source_file": "internal/installer/steps.go", "source_location": "L208", "weight": 1.0}, {"source": "installer_steps_installdirs", "target": "paths", "relation": "references", "confidence": "EXTRACTED", "source_file": "internal/installer/steps.go", "source_location": "L208", "weight": 1.0, "context": "parameter_type"}, {"source": "users_rokaskucinskas_development_ozy_internal_installer_steps_go", "target": "installer_steps_stepcreateinstallroot", "relation": "contains", "confidence": "EXTRACTED", "source_file": "internal/installer/steps.go", "source_location": "L212", "weight": 1.0}, {"source": "installer_steps_stepcreateinstallroot", "target": "installer_execcontext", "relation": "references", "confidence": "EXTRACTED", "source_file": "internal/installer/steps.go", "source_location": "L212", "weight": 1.0, "context": "parameter_type"}, {"source": "users_rokaskucinskas_development_ozy_internal_installer_steps_go", "target": "installer_steps_validinstallroot", "relation": "contains", "confidence": "EXTRACTED", "source_file": "internal/installer/steps.go", "source_location": "L221", "weight": 1.0}, {"source": "installer_steps_validinstallroot", "target": "installer_execcontext", "relation": "references", "confidence": "EXTRACTED", "source_file": "internal/installer/steps.go", "source_location": "L221", "weight": 1.0, "context": "parameter_type"}, {"source": "users_rokaskucinskas_development_ozy_internal_installer_steps_go", "target": "installer_steps_stepinstallozybinary", "relation": "contains", "confidence": "EXTRACTED", "source_file": "internal/installer/steps.go", "source_location": "L230", "weight": 1.0}, {"source": "installer_steps_stepinstallozybinary", "target": "installer_execcontext", "relation": "references", "confidence": "EXTRACTED", "source_file": "internal/installer/steps.go", "source_location": "L230", "weight": 1.0, "context": "parameter_type"}, {"source": "users_rokaskucinskas_development_ozy_internal_installer_steps_go", "target": "installer_steps_validbinary", "relation": "contains", "confidence": "EXTRACTED", "source_file": "internal/installer/steps.go", "source_location": "L254", "weight": 1.0}, {"source": "installer_steps_validbinary", "target": "installer_execcontext", "relation": "references", "confidence": "EXTRACTED", "source_file": "internal/installer/steps.go", "source_location": "L254", "weight": 1.0, "context": "parameter_type"}, {"source": "users_rokaskucinskas_development_ozy_internal_installer_steps_go", "target": "installer_steps_installref", "relation": "contains", "confidence": "EXTRACTED", "source_file": "internal/installer/steps.go", "source_location": "L259", "weight": 1.0}, {"source": "users_rokaskucinskas_development_ozy_internal_installer_steps_go", "target": "installer_steps_stepcreateorupdateconfig", "relation": "contains", "confidence": "EXTRACTED", "source_file": "internal/installer/steps.go", "source_location": "L266", "weight": 1.0}, {"source": "installer_steps_stepcreateorupdateconfig", "target": "installer_execcontext", "relation": "references", "confidence": "EXTRACTED", "source_file": "internal/installer/steps.go", "source_location": "L266", "weight": 1.0, "context": "parameter_type"}, {"source": "users_rokaskucinskas_development_ozy_internal_installer_steps_go", "target": "installer_steps_validconfig", "relation": "contains", "confidence": "EXTRACTED", "source_file": "internal/installer/steps.go", "source_location": "L270", "weight": 1.0}, {"source": "installer_steps_validconfig", "target": "installer_execcontext", "relation": "references", "confidence": "EXTRACTED", "source_file": "internal/installer/steps.go", "source_location": "L270", "weight": 1.0, "context": "parameter_type"}, {"source": "users_rokaskucinskas_development_ozy_internal_installer_steps_go", "target": "installer_steps_stepsetuppythonenvironment", "relation": "contains", "confidence": "EXTRACTED", "source_file": "internal/installer/steps.go", "source_location": "L278", "weight": 1.0}, {"source": "installer_steps_stepsetuppythonenvironment", "target": "installer_execcontext", "relation": "references", "confidence": "EXTRACTED", "source_file": "internal/installer/steps.go", "source_location": "L278", "weight": 1.0, "context": "parameter_type"}, {"source": "users_rokaskucinskas_development_ozy_internal_installer_steps_go", "target": "installer_steps_stepdownloadembeddingassets", "relation": "contains", "confidence": "EXTRACTED", "source_file": "internal/installer/steps.go", "source_location": "L305", "weight": 1.0}, {"source": "installer_steps_stepdownloadembeddingassets", "target": "installer_execcontext", "relation": "references", "confidence": "EXTRACTED", "source_file": "internal/installer/steps.go", "source_location": "L305", "weight": 1.0, "context": "parameter_type"}, {"source": "users_rokaskucinskas_development_ozy_internal_installer_steps_go", "target": "installer_steps_stepbuildorloadtoolcatalog", "relation": "contains", "confidence": "EXTRACTED", "source_file": "internal/installer/steps.go", "source_location": "L317", "weight": 1.0}, {"source": "installer_steps_stepbuildorloadtoolcatalog", "target": "installer_execcontext", "relation": "references", "confidence": "EXTRACTED", "source_file": "internal/installer/steps.go", "source_location": "L317", "weight": 1.0, "context": "parameter_type"}, {"source": "users_rokaskucinskas_development_ozy_internal_installer_steps_go", "target": "installer_steps_steprundoctor", "relation": "contains", "confidence": "EXTRACTED", "source_file": "internal/installer/steps.go", "source_location": "L328", "weight": 1.0}, {"source": "installer_steps_steprundoctor", "target": "installer_execcontext", "relation": "references", "confidence": "EXTRACTED", "source_file": "internal/installer/steps.go", "source_location": "L328", "weight": 1.0, "context": "parameter_type"}, {"source": "users_rokaskucinskas_development_ozy_internal_installer_steps_go", "target": "installer_steps_stepprintnextsteps", "relation": "contains", "confidence": "EXTRACTED", "source_file": "internal/installer/steps.go", "source_location": "L341", "weight": 1.0}, {"source": "installer_steps_stepprintnextsteps", "target": "installer_execcontext", "relation": "references", "confidence": "EXTRACTED", "source_file": "internal/installer/steps.go", "source_location": "L341", "weight": 1.0, "context": "parameter_type"}, {"source": "users_rokaskucinskas_development_ozy_internal_installer_steps_go", "target": "installer_steps_boollabel", "relation": "contains", "confidence": "EXTRACTED", "source_file": "internal/installer/steps.go", "source_location": "L373", "weight": 1.0}, {"source": "users_rokaskucinskas_development_ozy_internal_installer_steps_go", "target": "installer_steps_direxists", "relation": "contains", "confidence": "EXTRACTED", "source_file": "internal/installer/steps.go", "source_location": "L380", "weight": 1.0}, {"source": "installer_steps_stepnames", "target": "installer_steps_installsteps", "relation": "calls", "context": "call", "confidence": "EXTRACTED", "source_file": "internal/installer/steps.go", "source_location": "L165", "weight": 1.0}, {"source": "installer_steps_stepcreateinstallroot", "target": "installer_steps_installdirs", "relation": "calls", "context": "call", "confidence": "EXTRACTED", "source_file": "internal/installer/steps.go", "source_location": "L213", "weight": 1.0}, {"source": "installer_steps_validinstallroot", "target": "installer_steps_installdirs", "relation": "calls", "context": "call", "confidence": "EXTRACTED", "source_file": "internal/installer/steps.go", "source_location": "L222", "weight": 1.0}, {"source": "installer_steps_validinstallroot", "target": "installer_steps_direxists", "relation": "calls", "context": "call", "confidence": "EXTRACTED", "source_file": "internal/installer/steps.go", "source_location": "L223", "weight": 1.0}, {"source": "installer_steps_stepinstallozybinary", "target": "installer_steps_installref", "relation": "calls", "context": "call", "confidence": "EXTRACTED", "source_file": "internal/installer/steps.go", "source_location": "L231", "weight": 1.0}, {"source": "installer_steps_stepsetuppythonenvironment", "target": "installer_execcontext_allow", "relation": "calls", "context": "call", "confidence": "EXTRACTED", "source_file": "internal/installer/steps.go", "source_location": "L283", "weight": 1.0}, {"source": "installer_steps_stepprintnextsteps", "target": "installer_steps_boollabel", "relation": "calls", "context": "call", "confidence": "EXTRACTED", "source_file": "internal/installer/steps.go", "source_location": "L356", "weight": 1.0}, {"source": "installer_steps_stepprintnextsteps", "target": "installer_steps_validconfig", "relation": "calls", "context": "call", "confidence": "EXTRACTED", "source_file": "internal/installer/steps.go", "source_location": "L357", "weight": 1.0}], "raw_calls": [{"caller_nid": "installer_execcontext_allow", "callee": "askConsent", "is_member_call": false, "source_file": "/Users/rokaskucinskas/Development/ozy/internal/installer/steps.go", "source_location": "L58"}, {"caller_nid": "installer_execcontext_execute", "callee": "Done", "is_member_call": true, "source_file": "/Users/rokaskucinskas/Development/ozy/internal/installer/steps.go", "source_location": "L66"}, {"caller_nid": "installer_execcontext_execute", "callee": "valid", "is_member_call": true, "source_file": "/Users/rokaskucinskas/Development/ozy/internal/installer/steps.go", "source_location": "L66"}, {"caller_nid": "installer_execcontext_execute", "callee": "Skip", "is_member_call": true, "source_file": "/Users/rokaskucinskas/Development/ozy/internal/installer/steps.go", "source_location": "L67"}, {"caller_nid": "installer_execcontext_execute", "callee": "Logf", "is_member_call": true, "source_file": "/Users/rokaskucinskas/Development/ozy/internal/installer/steps.go", "source_location": "L68"}, {"caller_nid": "installer_execcontext_execute", "callee": "Start", "is_member_call": true, "source_file": "/Users/rokaskucinskas/Development/ozy/internal/installer/steps.go", "source_location": "L71"}, {"caller_nid": "installer_execcontext_execute", "callee": "Logf", "is_member_call": true, "source_file": "/Users/rokaskucinskas/Development/ozy/internal/installer/steps.go", "source_location": "L72"}, {"caller_nid": "installer_execcontext_execute", "callee": "run", "is_member_call": true, "source_file": "/Users/rokaskucinskas/Development/ozy/internal/installer/steps.go", "source_location": "L73"}, {"caller_nid": "installer_execcontext_execute", "callee": "Mark", "is_member_call": true, "source_file": "/Users/rokaskucinskas/Development/ozy/internal/installer/steps.go", "source_location": "L74"}, {"caller_nid": "installer_execcontext_execute", "callee": "Save", "is_member_call": true, "source_file": "/Users/rokaskucinskas/Development/ozy/internal/installer/steps.go", "source_location": "L75"}, {"caller_nid": "installer_execcontext_execute", "callee": "Fail", "is_member_call": true, "source_file": "/Users/rokaskucinskas/Development/ozy/internal/installer/steps.go", "source_location": "L76"}, {"caller_nid": "installer_execcontext_execute", "callee": "Path", "is_member_call": true, "source_file": "/Users/rokaskucinskas/Development/ozy/internal/installer/steps.go", "source_location": "L79"}, {"caller_nid": "installer_execcontext_execute", "callee": "Mark", "is_member_call": true, "source_file": "/Users/rokaskucinskas/Development/ozy/internal/installer/steps.go", "source_location": "L82"}, {"caller_nid": "installer_execcontext_execute", "callee": "Save", "is_member_call": true, "source_file": "/Users/rokaskucinskas/Development/ozy/internal/installer/steps.go", "source_location": "L83"}, {"caller_nid": "installer_execcontext_execute", "callee": "Errorf", "is_member_call": false, "source_file": "/Users/rokaskucinskas/Development/ozy/internal/installer/steps.go", "source_location": "L84"}, {"caller_nid": "installer_execcontext_execute", "callee": "Done", "is_member_call": true, "source_file": "/Users/rokaskucinskas/Development/ozy/internal/installer/steps.go", "source_location": "L86"}, {"caller_nid": "installer_execcontext_execute", "callee": "Logf", "is_member_call": true, "source_file": "/Users/rokaskucinskas/Development/ozy/internal/installer/steps.go", "source_location": "L87"}, {"caller_nid": "installer_steps_stepnames", "callee": "make", "is_member_call": false, "source_file": "/Users/rokaskucinskas/Development/ozy/internal/installer/steps.go", "source_location": "L166"}, {"caller_nid": "installer_steps_stepdetectplatform", "callee": "Logf", "is_member_call": true, "source_file": "/Users/rokaskucinskas/Development/ozy/internal/installer/steps.go", "source_location": "L176"}, {"caller_nid": "installer_steps_stepresolveinstalldirs", "callee": "Logf", "is_member_call": true, "source_file": "/Users/rokaskucinskas/Development/ozy/internal/installer/steps.go", "source_location": "L181"}, {"caller_nid": "installer_steps_stepcheckexistinginstall", "callee": "Logf", "is_member_call": true, "source_file": "/Users/rokaskucinskas/Development/ozy/internal/installer/steps.go", "source_location": "L187"}, {"caller_nid": "installer_steps_stepcheckexistinginstall", "callee": "Logf", "is_member_call": true, "source_file": "/Users/rokaskucinskas/Development/ozy/internal/installer/steps.go", "source_location": "L189"}, {"caller_nid": "installer_steps_stepcheckdependencies", "callee": "Logf", "is_member_call": true, "source_file": "/Users/rokaskucinskas/Development/ozy/internal/installer/steps.go", "source_location": "L196"}, {"caller_nid": "installer_steps_stepcheckdependencies", "callee": "Errorf", "is_member_call": false, "source_file": "/Users/rokaskucinskas/Development/ozy/internal/installer/steps.go", "source_location": "L198"}, {"caller_nid": "installer_steps_stepcreateinstallroot", "callee": "MkdirAll", "is_member_call": false, "source_file": "/Users/rokaskucinskas/Development/ozy/internal/installer/steps.go", "source_location": "L214"}, {"caller_nid": "installer_steps_stepcreateinstallroot", "callee": "Errorf", "is_member_call": false, "source_file": "/Users/rokaskucinskas/Development/ozy/internal/installer/steps.go", "source_location": "L215"}, {"caller_nid": "installer_steps_stepinstallozybinary", "callee": "Sayf", "is_member_call": true, "source_file": "/Users/rokaskucinskas/Development/ozy/internal/installer/steps.go", "source_location": "L232"}, {"caller_nid": "installer_steps_stepinstallozybinary", "callee": "LookupEnv", "is_member_call": false, "source_file": "/Users/rokaskucinskas/Development/ozy/internal/installer/steps.go", "source_location": "L235"}, {"caller_nid": "installer_steps_stepinstallozybinary", "callee": "Setenv", "is_member_call": false, "source_file": "/Users/rokaskucinskas/Development/ozy/internal/installer/steps.go", "source_location": "L236"}, {"caller_nid": "installer_steps_stepinstallozybinary", "callee": "Setenv", "is_member_call": false, "source_file": "/Users/rokaskucinskas/Development/ozy/internal/installer/steps.go", "source_location": "L239"}, {"caller_nid": "installer_steps_stepinstallozybinary", "callee": "Unsetenv", "is_member_call": false, "source_file": "/Users/rokaskucinskas/Development/ozy/internal/installer/steps.go", "source_location": "L241"}, {"caller_nid": "installer_steps_stepinstallozybinary", "callee": "run", "is_member_call": true, "source_file": "/Users/rokaskucinskas/Development/ozy/internal/installer/steps.go", "source_location": "L244"}, {"caller_nid": "installer_steps_stepinstallozybinary", "callee": "Errorf", "is_member_call": false, "source_file": "/Users/rokaskucinskas/Development/ozy/internal/installer/steps.go", "source_location": "L246"}, {"caller_nid": "installer_steps_stepinstallozybinary", "callee": "TrimSpace", "is_member_call": false, "source_file": "/Users/rokaskucinskas/Development/ozy/internal/installer/steps.go", "source_location": "L246"}, {"caller_nid": "installer_steps_validbinary", "callee": "fileExists", "is_member_call": false, "source_file": "/Users/rokaskucinskas/Development/ozy/internal/installer/steps.go", "source_location": "L254"}, {"caller_nid": "installer_steps_installref", "callee": "releaseVersion", "is_member_call": false, "source_file": "/Users/rokaskucinskas/Development/ozy/internal/installer/steps.go", "source_location": "L260"}, {"caller_nid": "installer_steps_stepcreateorupdateconfig", "callee": "Ensure", "is_member_call": true, "source_file": "/Users/rokaskucinskas/Development/ozy/internal/installer/steps.go", "source_location": "L267"}, {"caller_nid": "installer_steps_stepcreateorupdateconfig", "callee": "NewConfigManager", "is_member_call": false, "source_file": "/Users/rokaskucinskas/Development/ozy/internal/installer/steps.go", "source_location": "L267"}, {"caller_nid": "installer_steps_validconfig", "callee": "fileExists", "is_member_call": false, "source_file": "/Users/rokaskucinskas/Development/ozy/internal/installer/steps.go", "source_location": "L271"}, {"caller_nid": "installer_steps_validconfig", "callee": "Load", "is_member_call": false, "source_file": "/Users/rokaskucinskas/Development/ozy/internal/installer/steps.go", "source_location": "L274"}, {"caller_nid": "installer_steps_stepsetuppythonenvironment", "callee": "SemanticPlanned", "is_member_call": true, "source_file": "/Users/rokaskucinskas/Development/ozy/internal/installer/steps.go", "source_location": "L279"}, {"caller_nid": "installer_steps_stepsetuppythonenvironment", "callee": "Sayf", "is_member_call": true, "source_file": "/Users/rokaskucinskas/Development/ozy/internal/installer/steps.go", "source_location": "L280"}, {"caller_nid": "installer_steps_stepsetuppythonenvironment", "callee": "Sayf", "is_member_call": true, "source_file": "/Users/rokaskucinskas/Development/ozy/internal/installer/steps.go", "source_location": "L284"}, {"caller_nid": "installer_steps_stepsetuppythonenvironment", "callee": "Provision", "is_member_call": false, "source_file": "/Users/rokaskucinskas/Development/ozy/internal/installer/steps.go", "source_location": "L287"}, {"caller_nid": "installer_steps_stepsetuppythonenvironment", "callee": "Is", "is_member_call": false, "source_file": "/Users/rokaskucinskas/Development/ozy/internal/installer/steps.go", "source_location": "L293"}, {"caller_nid": "installer_steps_stepsetuppythonenvironment", "callee": "Sayf", "is_member_call": true, "source_file": "/Users/rokaskucinskas/Development/ozy/internal/installer/steps.go", "source_location": "L294"}, {"caller_nid": "installer_steps_stepsetuppythonenvironment", "callee": "Errorf", "is_member_call": false, "source_file": "/Users/rokaskucinskas/Development/ozy/internal/installer/steps.go", "source_location": "L298"}, {"caller_nid": "installer_steps_stepsetuppythonenvironment", "callee": "Logf", "is_member_call": true, "source_file": "/Users/rokaskucinskas/Development/ozy/internal/installer/steps.go", "source_location": "L301"}, {"caller_nid": "installer_steps_stepdownloadembeddingassets", "callee": "Sayf", "is_member_call": true, "source_file": "/Users/rokaskucinskas/Development/ozy/internal/installer/steps.go", "source_location": "L307"}, {"caller_nid": "installer_steps_stepdownloadembeddingassets", "callee": "Sayf", "is_member_call": true, "source_file": "/Users/rokaskucinskas/Development/ozy/internal/installer/steps.go", "source_location": "L313"}, {"caller_nid": "installer_steps_stepbuildorloadtoolcatalog", "callee": "Join", "is_member_call": false, "source_file": "/Users/rokaskucinskas/Development/ozy/internal/installer/steps.go", "source_location": "L318"}, {"caller_nid": "installer_steps_stepbuildorloadtoolcatalog", "callee": "NewFile", "is_member_call": false, "source_file": "/Users/rokaskucinskas/Development/ozy/internal/installer/steps.go", "source_location": "L319"}, {"caller_nid": "installer_steps_stepbuildorloadtoolcatalog", "callee": "Errorf", "is_member_call": false, "source_file": "/Users/rokaskucinskas/Development/ozy/internal/installer/steps.go", "source_location": "L320"}, {"caller_nid": "installer_steps_stepbuildorloadtoolcatalog", "callee": "Sayf", "is_member_call": true, "source_file": "/Users/rokaskucinskas/Development/ozy/internal/installer/steps.go", "source_location": "L324"}, {"caller_nid": "installer_steps_steprundoctor", "callee": "run", "is_member_call": true, "source_file": "/Users/rokaskucinskas/Development/ozy/internal/installer/steps.go", "source_location": "L329"}, {"caller_nid": "installer_steps_steprundoctor", "callee": "TrimSpace", "is_member_call": false, "source_file": "/Users/rokaskucinskas/Development/ozy/internal/installer/steps.go", "source_location": "L330"}, {"caller_nid": "installer_steps_steprundoctor", "callee": "Logf", "is_member_call": true, "source_file": "/Users/rokaskucinskas/Development/ozy/internal/installer/steps.go", "source_location": "L332"}, {"caller_nid": "installer_steps_steprundoctor", "callee": "Sayf", "is_member_call": true, "source_file": "/Users/rokaskucinskas/Development/ozy/internal/installer/steps.go", "source_location": "L336"}, {"caller_nid": "installer_steps_stepprintnextsteps", "callee": "Fprintln", "is_member_call": false, "source_file": "/Users/rokaskucinskas/Development/ozy/internal/installer/steps.go", "source_location": "L348"}, {"caller_nid": "installer_steps_stepprintnextsteps", "callee": "Fprintln", "is_member_call": false, "source_file": "/Users/rokaskucinskas/Development/ozy/internal/installer/steps.go", "source_location": "L349"}, {"caller_nid": "installer_steps_stepprintnextsteps", "callee": "Fprintf", "is_member_call": false, "source_file": "/Users/rokaskucinskas/Development/ozy/internal/installer/steps.go", "source_location": "L350"}, {"caller_nid": "installer_steps_stepprintnextsteps", "callee": "Fprintf", "is_member_call": false, "source_file": "/Users/rokaskucinskas/Development/ozy/internal/installer/steps.go", "source_location": "L351"}, {"caller_nid": "installer_steps_stepprintnextsteps", "callee": "Fprintf", "is_member_call": false, "source_file": "/Users/rokaskucinskas/Development/ozy/internal/installer/steps.go", "source_location": "L352"}, {"caller_nid": "installer_steps_stepprintnextsteps", "callee": "Fprintf", "is_member_call": false, "source_file": "/Users/rokaskucinskas/Development/ozy/internal/installer/steps.go", "source_location": "L353"}, {"caller_nid": "installer_steps_stepprintnextsteps", "callee": "Fprintln", "is_member_call": false, "source_file": "/Users/rokaskucinskas/Development/ozy/internal/installer/steps.go", "source_location": "L354"}, {"caller_nid": "installer_steps_stepprintnextsteps", "callee": "Fprintln", "is_member_call": false, "source_file": "/Users/rokaskucinskas/Development/ozy/internal/installer/steps.go", "source_location": "L355"}, {"caller_nid": "installer_steps_stepprintnextsteps", "callee": "Fprintf", "is_member_call": false, "source_file": "/Users/rokaskucinskas/Development/ozy/internal/installer/steps.go", "source_location": "L356"}, {"caller_nid": "installer_steps_stepprintnextsteps", "callee": "Reachable", "is_member_call": true, "source_file": "/Users/rokaskucinskas/Development/ozy/internal/installer/steps.go", "source_location": "L356"}, {"caller_nid": "installer_steps_stepprintnextsteps", "callee": "Fprintf", "is_member_call": false, "source_file": "/Users/rokaskucinskas/Development/ozy/internal/installer/steps.go", "source_location": "L357"}, {"caller_nid": "installer_steps_stepprintnextsteps", "callee": "Fprintf", "is_member_call": false, "source_file": "/Users/rokaskucinskas/Development/ozy/internal/installer/steps.go", "source_location": "L358"}, {"caller_nid": "installer_steps_stepprintnextsteps", "callee": "Fprintf", "is_member_call": false, "source_file": "/Users/rokaskucinskas/Development/ozy/internal/installer/steps.go", "source_location": "L359"}, {"caller_nid": "installer_steps_stepprintnextsteps", "callee": "Fprintln", "is_member_call": false, "source_file": "/Users/rokaskucinskas/Development/ozy/internal/installer/steps.go", "source_location": "L360"}, {"caller_nid": "installer_steps_stepprintnextsteps", "callee": "Fprintln", "is_member_call": false, "source_file": "/Users/rokaskucinskas/Development/ozy/internal/installer/steps.go", "source_location": "L361"}, {"caller_nid": "installer_steps_stepprintnextsteps", "callee": "Fprintln", "is_member_call": false, "source_file": "/Users/rokaskucinskas/Development/ozy/internal/installer/steps.go", "source_location": "L362"}, {"caller_nid": "installer_steps_stepprintnextsteps", "callee": "Fprintln", "is_member_call": false, "source_file": "/Users/rokaskucinskas/Development/ozy/internal/installer/steps.go", "source_location": "L363"}, {"caller_nid": "installer_steps_stepprintnextsteps", "callee": "Fprintln", "is_member_call": false, "source_file": "/Users/rokaskucinskas/Development/ozy/internal/installer/steps.go", "source_location": "L364"}, {"caller_nid": "installer_steps_stepprintnextsteps", "callee": "Fprintln", "is_member_call": false, "source_file": "/Users/rokaskucinskas/Development/ozy/internal/installer/steps.go", "source_location": "L365"}, {"caller_nid": "installer_steps_stepprintnextsteps", "callee": "Fprintln", "is_member_call": false, "source_file": "/Users/rokaskucinskas/Development/ozy/internal/installer/steps.go", "source_location": "L366"}, {"caller_nid": "installer_steps_stepprintnextsteps", "callee": "Fprintln", "is_member_call": false, "source_file": "/Users/rokaskucinskas/Development/ozy/internal/installer/steps.go", "source_location": "L367"}, {"caller_nid": "installer_steps_stepprintnextsteps", "callee": "Fprintf", "is_member_call": false, "source_file": "/Users/rokaskucinskas/Development/ozy/internal/installer/steps.go", "source_location": "L368"}, {"caller_nid": "installer_steps_stepprintnextsteps", "callee": "Fprintf", "is_member_call": false, "source_file": "/Users/rokaskucinskas/Development/ozy/internal/installer/steps.go", "source_location": "L369"}, {"caller_nid": "installer_steps_stepprintnextsteps", "callee": "Path", "is_member_call": true, "source_file": "/Users/rokaskucinskas/Development/ozy/internal/installer/steps.go", "source_location": "L369"}, {"caller_nid": "installer_steps_direxists", "callee": "Stat", "is_member_call": false, "source_file": "/Users/rokaskucinskas/Development/ozy/internal/installer/steps.go", "source_location": "L381"}, {"caller_nid": "installer_steps_direxists", "callee": "IsDir", "is_member_call": true, "source_file": "/Users/rokaskucinskas/Development/ozy/internal/installer/steps.go", "source_location": "L382"}]}